{
	"nodes": [
		{
			"id": -100,
			"name": "LEUR LOMANTO JÚNIOR",
			"desc": "116396.16"
		},
		{
			"id": -4,
			"name": "Voltar",
			"val": 50000
		},
		{
			"id": -3,
			"name": "Placeholder",
			"val": 1
		},
		{
			"id": -3,
			"name": "Visualizar fichas",
			"val": 50000
		},
		{
			"id": "LUCAS GEDEON SAMPAIO",
			"name": "LUCAS GEDEON SAMPAIO",
			"val": 56.040713616082165,
			"desc": "16500.00",
			"group": "LUCAS GEDEON SAMPAIO"
		},
		{
			"id": 30356,
			"name": "5500.00",
			"val": 123.43196875331004,
			"group": "LUCAS GEDEON SAMPAIO"
		},
		{
			"id": 30319,
			"name": "5500.00",
			"val": 123.43196875331004,
			"group": "LUCAS GEDEON SAMPAIO"
		},
		{
			"id": 30291,
			"name": "5500.00",
			"val": 123.43196875331004,
			"group": "LUCAS GEDEON SAMPAIO"
		},
		{
			"id": "Cia Aérea - TAM",
			"name": "Cia Aérea - TAM",
			"val": 57.79769094621892,
			"desc": "22372.25",
			"group": "Cia Aérea - TAM"
		},
		{
			"id": 30346,
			"name": "1115.08",
			"val": 136.35018449863867,
			"group": "Cia Aérea - TAM"
		},
		{
			"id": 30378,
			"name": "30.00",
			"val": 66.09305198180392,
			"group": "Cia Aérea - TAM"
		},
		{
			"id": 30316,
			"name": "1402.39",
			"val": 140.80507130259753,
			"group": "Cia Aérea - TAM"
		},
		{
			"id": 30381,
			"name": "779.00",
			"val": 129.38039777483004,
			"group": "Cia Aérea - TAM"
		},
		{
			"id": 30377,
			"name": "30.00",
			"val": 66.09305198180392,
			"group": "Cia Aérea - TAM"
		},
		{
			"id": 30348,
			"name": "555.08",
			"val": 122.79481823220533,
			"group": "Cia Aérea - TAM"
		},
		{
			"id": 30347,
			"name": "553.49",
			"val": 122.73907549804272,
			"group": "Cia Aérea - TAM"
		},
		{
			"id": 30313,
			"name": "877.98",
			"val": 131.70474771295665,
			"group": "Cia Aérea - TAM"
		},
		{
			"id": 30343,
			"name": "409.39",
			"val": 116.87877429330929,
			"group": "Cia Aérea - TAM"
		},
		{
			"id": 30388,
			"name": "669.39",
			"val": 126.43360386627548,
			"group": "Cia Aérea - TAM"
		},
		{
			"id": 30376,
			"name": "45.00",
			"val": 73.97216732262086,
			"group": "Cia Aérea - TAM"
		},
		{
			"id": 30345,
			"name": "555.08",
			"val": 122.79481823220533,
			"group": "Cia Aérea - TAM"
		},
		{
			"id": 30353,
			"name": "478.98",
			"val": 119.92946099395948,
			"group": "Cia Aérea - TAM"
		},
		{
			"id": 30383,
			"name": "975.90",
			"val": 133.75944625131882,
			"group": "Cia Aérea - TAM"
		},
		{
			"id": 30341,
			"name": "724.98",
			"val": 127.98385786446458,
			"group": "Cia Aérea - TAM"
		},
		{
			"id": 30380,
			"name": "30.00",
			"val": 66.09305198180392,
			"group": "Cia Aérea - TAM"
		},
		{
			"id": 30382,
			"name": "695.00",
			"val": 127.16318908898234,
			"group": "Cia Aérea - TAM"
		},
		{
			"id": 30351,
			"name": "501.39",
			"val": 120.8180101722964,
			"group": "Cia Aérea - TAM"
		},
		{
			"id": 30379,
			"name": "30.00",
			"val": 66.09305198180392,
			"group": "Cia Aérea - TAM"
		},
		{
			"id": 30318,
			"name": "724.98",
			"val": 127.98385786446458,
			"group": "Cia Aérea - TAM"
		},
		{
			"id": 30344,
			"name": "559.39",
			"val": 122.94512032208415,
			"group": "Cia Aérea - TAM"
		},
		{
			"id": 30385,
			"name": "1529.39",
			"val": 142.48967666727566,
			"group": "Cia Aérea - TAM"
		},
		{
			"id": 30352,
			"name": "501.39",
			"val": 120.8180101722964,
			"group": "Cia Aérea - TAM"
		},
		{
			"id": 30354,
			"name": "618.98",
			"val": 124.91217437421207,
			"group": "Cia Aérea - TAM"
		},
		{
			"id": 30342,
			"name": "724.98",
			"val": 127.98385786446458,
			"group": "Cia Aérea - TAM"
		},
		{
			"id": 30317,
			"name": "930.39",
			"val": 132.83143260798883,
			"group": "Cia Aérea - TAM"
		},
		{
			"id": 30375,
			"name": "30.00",
			"val": 66.09305198180392,
			"group": "Cia Aérea - TAM"
		},
		{
			"id": 30314,
			"name": "948.98",
			"val": 133.21587850572084,
			"group": "Cia Aérea - TAM"
		},
		{
			"id": 30350,
			"name": "913.49",
			"val": 132.47521106638922,
			"group": "Cia Aérea - TAM"
		},
		{
			"id": 30384,
			"name": "741.98",
			"val": 128.43426375131156,
			"group": "Cia Aérea - TAM"
		},
		{
			"id": 30349,
			"name": "613.98",
			"val": 124.75456669861916,
			"group": "Cia Aérea - TAM"
		},
		{
			"id": 30355,
			"name": "849.84",
			"val": 131.07172693459324,
			"group": "Cia Aérea - TAM"
		},
		{
			"id": 30315,
			"name": "814.98",
			"val": 130.257814752416,
			"group": "Cia Aérea - TAM"
		},
		{
			"id": 30386,
			"name": "740.39",
			"val": 128.39257732745335,
			"group": "Cia Aérea - TAM"
		},
		{
			"id": 30387,
			"name": "670.98",
			"val": 126.47970659121104,
			"group": "Cia Aérea - TAM"
		},
		{
			"id": "SIN- SISTEMAS INTELIGENTES LTDA - ME",
			"name": "SIN- SISTEMAS INTELIGENTES LTDA - ME",
			"val": 42.75300123653271,
			"desc": "1650.00",
			"group": "SIN- SISTEMAS INTELIGENTES LTDA - ME"
		},
		{
			"id": 30320,
			"name": "550.00",
			"val": 9.043196875331004,
			"group": "SIN- SISTEMAS INTELIGENTES LTDA - ME"
		},
		{
			"id": 30357,
			"name": "550.00",
			"val": 9.043196875331004,
			"group": "SIN- SISTEMAS INTELIGENTES LTDA - ME"
		},
		{
			"id": 30292,
			"name": "550.00",
			"val": 9.043196875331004,
			"group": "SIN- SISTEMAS INTELIGENTES LTDA - ME"
		},
		{
			"id": "MEIO MUNDO COMUNICAÇÃO TECNOLOGIA E INOVAÇÃO LTDA-ME",
			"name": "MEIO MUNDO COMUNICAÇÃO TECNOLOGIA E INOVAÇÃO LTDA-ME",
			"val": 54.88268714730222,
			"desc": "13500.00",
			"group": "MEIO MUNDO COMUNICAÇÃO TECNOLOGIA E INOVAÇÃO LTDA-ME"
		},
		{
			"id": 30331,
			"name": "4500.00",
			"val": 98.63673787193427,
			"group": "MEIO MUNDO COMUNICAÇÃO TECNOLOGIA E INOVAÇÃO LTDA-ME"
		},
		{
			"id": 30364,
			"name": "4500.00",
			"val": 98.63673787193427,
			"group": "MEIO MUNDO COMUNICAÇÃO TECNOLOGIA E INOVAÇÃO LTDA-ME"
		},
		{
			"id": 30332,
			"name": "4500.00",
			"val": 98.63673787193427,
			"group": "MEIO MUNDO COMUNICAÇÃO TECNOLOGIA E INOVAÇÃO LTDA-ME"
		},
		{
			"id": "CELULAR FUNCIONAL",
			"name": "CELULAR FUNCIONAL",
			"val": 38.272812624694936,
			"desc": "759.13",
			"group": "CELULAR FUNCIONAL"
		},
		{
			"id": 30367,
			"name": "9.09",
			"val": 1.4553492013405842,
			"group": "CELULAR FUNCIONAL"
		},
		{
			"id": 30300,
			"name": "77.08",
			"val": 2.86486811452638,
			"group": "CELULAR FUNCIONAL"
		},
		{
			"id": 30333,
			"name": "14.08",
			"val": 1.7438774666858994,
			"group": "CELULAR FUNCIONAL"
		},
		{
			"id": 30301,
			"name": "22.20",
			"val": 2.0441138669894263,
			"group": "CELULAR FUNCIONAL"
		},
		{
			"id": 30334,
			"name": "319.12",
			"val": 3.801653235418165,
			"group": "CELULAR FUNCIONAL"
		},
		{
			"id": 30366,
			"name": "316.93",
			"val": 3.7971126167397413,
			"group": "CELULAR FUNCIONAL"
		},
		{
			"id": 30365,
			"name": "0.63",
			"val": -0.304653217386605,
			"group": "CELULAR FUNCIONAL"
		},
		{
			"id": "CASCOL COMBUSTIVEIS PARA VEICULOS LTDA",
			"name": "CASCOL COMBUSTIVEIS PARA VEICULOS LTDA",
			"val": 35.01968358998196,
			"desc": "432.01",
			"group": "CASCOL COMBUSTIVEIS PARA VEICULOS LTDA"
		},
		{
			"id": 30358,
			"name": "232.01",
			"val": 2.04384510245679,
			"group": "CASCOL COMBUSTIVEIS PARA VEICULOS LTDA"
		},
		{
			"id": 30324,
			"name": "200.00",
			"val": 1.9881359368535931,
			"group": "CASCOL COMBUSTIVEIS PARA VEICULOS LTDA"
		},
		{
			"id": "JARJOUR FILIAL - 206 NORTE",
			"name": "JARJOUR FILIAL - 206 NORTE",
			"val": 28.91527476198352,
			"desc": "150.00",
			"group": "JARJOUR FILIAL - 206 NORTE"
		},
		{
			"id": 30360,
			"name": "150.00",
			"val": 0.6528273777167044,
			"group": "JARJOUR FILIAL - 206 NORTE"
		},
		{
			"id": "WMS COMERCIO DE ARTIGOS DE PAPELARIA LTDA-ME",
			"name": "WMS COMERCIO DE ARTIGOS DE PAPELARIA LTDA-ME",
			"val": 36.39423407175365,
			"desc": "548.20",
			"group": "WMS COMERCIO DE ARTIGOS DE PAPELARIA LTDA-ME"
		},
		{
			"id": 30321,
			"name": "287.00",
			"val": 2.6948217115791495,
			"group": "WMS COMERCIO DE ARTIGOS DE PAPELARIA LTDA-ME"
		},
		{
			"id": 30293,
			"name": "261.20",
			"val": 2.649969386441969,
			"group": "WMS COMERCIO DE ARTIGOS DE PAPELARIA LTDA-ME"
		},
		{
			"id": "CORREIOS - TELEGRAMA",
			"name": "CORREIOS - TELEGRAMA",
			"val": 14.267260616043586,
			"desc": "11.85",
			"group": "CORREIOS - TELEGRAMA"
		},
		{
			"id": 30372,
			"name": "11.85",
			"val": 0.025447124903203108,
			"group": "CORREIOS - TELEGRAMA"
		},
		{
			"id": "CORREIOS - ENCOMENDA PAC",
			"name": "CORREIOS - ENCOMENDA PAC",
			"val": 27.378446485481245,
			"desc": "114.93",
			"group": "CORREIOS - ENCOMENDA PAC"
		},
		{
			"id": 30337,
			"name": "51.86",
			"val": 0.39417140130792583,
			"group": "CORREIOS - ENCOMENDA PAC"
		},
		{
			"id": 30371,
			"name": "63.07",
			"val": 0.4137072759321245,
			"group": "CORREIOS - ENCOMENDA PAC"
		},
		{
			"id": "POSTO DE COMBUSTIVEIS RODOVIARIA LTDA",
			"name": "POSTO DE COMBUSTIVEIS RODOVIARIA LTDA",
			"val": 30.575424759098897,
			"desc": "200.00",
			"group": "POSTO DE COMBUSTIVEIS RODOVIARIA LTDA"
		},
		{
			"id": 30329,
			"name": "200.00",
			"val": 0.9204119982655925,
			"group": "POSTO DE COMBUSTIVEIS RODOVIARIA LTDA"
		},
		{
			"id": "Cia Aérea - AVIANCA",
			"name": "Cia Aérea - AVIANCA",
			"val": 45.058872843024794,
			"desc": "2460.47",
			"group": "Cia Aérea - AVIANCA"
		},
		{
			"id": 30307,
			"name": "903.49",
			"val": 14.545921450289637,
			"group": "Cia Aérea - AVIANCA"
		},
		{
			"id": 30310,
			"name": "49.00",
			"val": 8.317353498055516,
			"group": "Cia Aérea - AVIANCA"
		},
		{
			"id": 30309,
			"name": "708.49",
			"val": 14.026321239551502,
			"group": "Cia Aérea - AVIANCA"
		},
		{
			"id": 30308,
			"name": "799.49",
			"val": 14.28456878123709,
			"group": "Cia Aérea - AVIANCA"
		},
		{
			"id": "ELO COMERCIO E SERVICOS LTDA",
			"name": "ELO COMERCIO E SERVICOS LTDA",
			"val": 30.57629031120865,
			"desc": "200.03",
			"group": "ELO COMERCIO E SERVICOS LTDA"
		},
		{
			"id": 30327,
			"name": "200.03",
			"val": 0.920576119688474,
			"group": "ELO COMERCIO E SERVICOS LTDA"
		},
		{
			"id": "RAMAL",
			"name": "RAMAL",
			"val": 28.855333132397174,
			"desc": "148.45",
			"group": "RAMAL"
		},
		{
			"id": 30335,
			"name": "41.81",
			"val": 0.4813580817457182,
			"group": "RAMAL"
		},
		{
			"id": 30368,
			"name": "36.99",
			"val": 0.4655642379675406,
			"group": "RAMAL"
		},
		{
			"id": 30302,
			"name": "69.65",
			"val": 0.5471632807536388,
			"group": "RAMAL"
		},
		{
			"id": "Coelba Grupo Neoenergia",
			"name": "Coelba Grupo Neoenergia",
			"val": 35.687125773075195,
			"desc": "484.98",
			"group": "Coelba Grupo Neoenergia"
		},
		{
			"id": 30290,
			"name": "484.98",
			"val": 2.605044685353562,
			"group": "Coelba Grupo Neoenergia"
		},
		{
			"id": "AUTO POSTO ALMENARA LTDA",
			"name": "AUTO POSTO ALMENARA LTDA",
			"val": 31.170380410049,
			"desc": "221.72",
			"group": "AUTO POSTO ALMENARA LTDA"
		},
		{
			"id": 30323,
			"name": "201.72",
			"val": 1.0220178785949579,
			"group": "AUTO POSTO ALMENARA LTDA"
		},
		{
			"id": 30294,
			"name": "20.00",
			"val": 0.5769287412772358,
			"group": "AUTO POSTO ALMENARA LTDA"
		},
		{
			"id": "CORREIOS - SEDEX 12",
			"name": "CORREIOS - SEDEX 12",
			"val": 26.27942243332379,
			"desc": "95.00",
			"group": "CORREIOS - SEDEX 12"
		},
		{
			"id": 30338,
			"name": "95.00",
			"val": 0.3757674850048811,
			"group": "CORREIOS - SEDEX 12"
		},
		{
			"id": "TELEFÔNICA BRASIL S.A. - VIVO",
			"name": "TELEFÔNICA BRASIL S.A. - VIVO",
			"val": 31.40724597758018,
			"desc": "231.01",
			"group": "TELEFÔNICA BRASIL S.A. - VIVO"
		},
		{
			"id": 30369,
			"name": "231.01",
			"val": 1.09204469302741,
			"group": "TELEFÔNICA BRASIL S.A. - VIVO"
		},
		{
			"id": "Cia Aérea - PASSAREDO",
			"name": "Cia Aérea - PASSAREDO",
			"val": 41.07486971534483,
			"desc": "1233.65",
			"group": "Cia Aérea - PASSAREDO"
		},
		{
			"id": 30312,
			"name": "543.57",
			"val": 6.748695845094487,
			"group": "Cia Aérea - PASSAREDO"
		},
		{
			"id": 30311,
			"name": "690.08",
			"val": 7.004416590290471,
			"group": "Cia Aérea - PASSAREDO"
		},
		{
			"id": "AUTO SHOPPING QL 06 COM. DE DER. DE PETROLEO LTDA",
			"name": "AUTO SHOPPING QL 06 COM. DE DER. DE PETROLEO LTDA",
			"val": 34.85698207066449,
			"desc": "420.00",
			"group": "AUTO SHOPPING QL 06 COM. DE DER. DE PETROLEO LTDA"
		},
		{
			"id": 30296,
			"name": "210.00",
			"val": 1.950664207576492,
			"group": "AUTO SHOPPING QL 06 COM. DE DER. DE PETROLEO LTDA"
		},
		{
			"id": 30295,
			"name": "210.00",
			"val": 1.950664207576492,
			"group": "AUTO SHOPPING QL 06 COM. DE DER. DE PETROLEO LTDA"
		},
		{
			"id": "CORREIOS - SEDEX CONVENCIONAL",
			"name": "CORREIOS - SEDEX CONVENCIONAL",
			"val": 23.5217625915516,
			"desc": "58.91",
			"group": "CORREIOS - SEDEX CONVENCIONAL"
		},
		{
			"id": 30303,
			"name": "58.91",
			"val": 0.20856367065875472,
			"group": "CORREIOS - SEDEX CONVENCIONAL"
		},
		{
			"id": "FERREIRA COMBUSTIVEIS LTDA",
			"name": "FERREIRA COMBUSTIVEIS LTDA",
			"val": 32.09080281697691,
			"desc": "260.06",
			"group": "FERREIRA COMBUSTIVEIS LTDA"
		},
		{
			"id": 30328,
			"name": "260.06",
			"val": 1.2561280590972561,
			"group": "FERREIRA COMBUSTIVEIS LTDA"
		},
		{
			"id": "UNIDAS LOCADORA DE VEÍCULOS",
			"name": "UNIDAS LOCADORA DE VEÍCULOS",
			"val": 52.03798496590943,
			"desc": "8246.10",
			"group": "UNIDAS LOCADORA DE VEÍCULOS"
		},
		{
			"id": 30306,
			"name": "2748.70",
			"val": 56.718775957035895,
			"group": "UNIDAS LOCADORA DE VEÍCULOS"
		},
		{
			"id": 30374,
			"name": "2748.70",
			"val": 56.718775957035895,
			"group": "UNIDAS LOCADORA DE VEÍCULOS"
		},
		{
			"id": 30340,
			"name": "2748.70",
			"val": 56.718775957035895,
			"group": "UNIDAS LOCADORA DE VEÍCULOS"
		},
		{
			"id": "MULTIPLICAR E SERVIÇOS LTDA EPP",
			"name": "MULTIPLICAR E SERVIÇOS LTDA EPP",
			"val": 56.212988503649704,
			"desc": "17000.00",
			"group": "MULTIPLICAR E SERVIÇOS LTDA EPP"
		},
		{
			"id": 30305,
			"name": "8500.00",
			"val": 133.60024347428595,
			"group": "MULTIPLICAR E SERVIÇOS LTDA EPP"
		},
		{
			"id": 30373,
			"name": "8500.00",
			"val": 133.60024347428595,
			"group": "MULTIPLICAR E SERVIÇOS LTDA EPP"
		},
		{
			"id": "MULTIPLICAR SERVICOS LTDA",
			"name": "MULTIPLICAR SERVICOS LTDA",
			"val": 52.212988503649704,
			"desc": "8500.00",
			"group": "MULTIPLICAR SERVICOS LTDA"
		},
		{
			"id": 30339,
			"name": "8500.00",
			"val": 66.80012173714297,
			"group": "MULTIPLICAR SERVICOS LTDA"
		},
		{
			"id": "POSTO KALILANDIA LTDA",
			"name": "POSTO KALILANDIA LTDA",
			"val": 31.898576104160995,
			"desc": "251.54",
			"group": "POSTO KALILANDIA LTDA"
		},
		{
			"id": 30298,
			"name": "251.54",
			"val": 1.207697398024613,
			"group": "POSTO KALILANDIA LTDA"
		},
		{
			"id": "CASTRO OLIVEIRA ADVOGADOS",
			"name": "CASTRO OLIVEIRA ADVOGADOS",
			"val": 56.5428371444176,
			"desc": "18000.00",
			"group": "CASTRO OLIVEIRA ADVOGADOS"
		},
		{
			"id": 30363,
			"name": "6000.00",
			"val": 136.01344501381118,
			"group": "CASTRO OLIVEIRA ADVOGADOS"
		},
		{
			"id": 30299,
			"name": "6000.00",
			"val": 136.01344501381118,
			"group": "CASTRO OLIVEIRA ADVOGADOS"
		},
		{
			"id": 30330,
			"name": "6000.00",
			"val": 136.01344501381118,
			"group": "CASTRO OLIVEIRA ADVOGADOS"
		},
		{
			"id": "AUTO POSTO AEROPORTO LTDA",
			"name": "AUTO POSTO AEROPORTO LTDA",
			"val": 26.575424759098897,
			"desc": "100.00",
			"group": "AUTO POSTO AEROPORTO LTDA"
		},
		{
			"id": 30322,
			"name": "100.00",
			"val": 0.4,
			"group": "AUTO POSTO AEROPORTO LTDA"
		},
		{
			"id": "PHAB DERIVADOS DE PETROLEO LTDA",
			"name": "PHAB DERIVADOS DE PETROLEO LTDA",
			"val": 31.627802826598337,
			"desc": "240.01",
			"group": "PHAB DERIVADOS DE PETROLEO LTDA"
		},
		{
			"id": 30361,
			"name": "240.01",
			"val": 1.1425576863169966,
			"group": "PHAB DERIVADOS DE PETROLEO LTDA"
		},
		{
			"id": "COMERCIO DE PETROLEO RSSILVA LTDA",
			"name": "COMERCIO DE PETROLEO RSSILVA LTDA",
			"val": 34.822114867708635,
			"desc": "417.47",
			"group": "COMERCIO DE PETROLEO RSSILVA LTDA"
		},
		{
			"id": 30325,
			"name": "240.00",
			"val": 1.9873335741546883,
			"group": "COMERCIO DE PETROLEO RSSILVA LTDA"
		},
		{
			"id": 30326,
			"name": "177.47",
			"val": 1.8778843851711906,
			"group": "COMERCIO DE PETROLEO RSSILVA LTDA"
		},
		{
			"id": "ITAPOAN DISTRIB. DE DER. DE PETROLEO LTDA",
			"name": "ITAPOAN DISTRIB. DE DER. DE PETROLEO LTDA",
			"val": 35.99876005074679,
			"desc": "511.89",
			"group": "ITAPOAN DISTRIB. DE DER. DE PETROLEO LTDA"
		},
		{
			"id": 30359,
			"name": "260.02",
			"val": 2.4724356145628494,
			"group": "ITAPOAN DISTRIB. DE DER. DE PETROLEO LTDA"
		},
		{
			"id": 30297,
			"name": "251.87",
			"val": 2.4582764179639867,
			"group": "ITAPOAN DISTRIB. DE DER. DE PETROLEO LTDA"
		},
		{
			"id": "ATACADAO DO PAPEL EIRELI",
			"name": "ATACADAO DO PAPEL EIRELI",
			"val": 38.453831936043514,
			"desc": "783.32",
			"group": "ATACADAO DO PAPEL EIRELI"
		},
		{
			"id": 30289,
			"name": "783.32",
			"val": 4.533760932167761,
			"group": "ATACADAO DO PAPEL EIRELI"
		},
		{
			"id": "Chicago Prime Parrilla Ltda-ME",
			"name": "Chicago Prime Parrilla Ltda-ME",
			"val": 25.91653413231938,
			"desc": "89.21",
			"group": "Chicago Prime Parrilla Ltda-ME"
		},
		{
			"id": 30304,
			"name": "89.21",
			"val": 0.347992783694285,
			"group": "Chicago Prime Parrilla Ltda-ME"
		},
		{
			"id": "CORREIOS - CARTA COMERCIAL",
			"name": "CORREIOS - CARTA COMERCIAL",
			"val": 7.853896495899543,
			"desc": "3.90",
			"group": "CORREIOS - CARTA COMERCIAL"
		},
		{
			"id": 30370,
			"name": "1.95",
			"val": 0.0022622699686276402,
			"group": "CORREIOS - CARTA COMERCIAL"
		},
		{
			"id": 30336,
			"name": "1.95",
			"val": 0.0022622699686276402,
			"group": "CORREIOS - CARTA COMERCIAL"
		},
		{
			"id": "TIC COMERCIO DE COMBUSTIVEIS LTDA ME",
			"name": "TIC COMERCIO DE COMBUSTIVEIS LTDA ME",
			"val": 30.57744417877831,
			"desc": "200.07",
			"group": "TIC COMERCIO DE COMBUSTIVEIS LTDA ME"
		},
		{
			"id": 30362,
			"name": "200.07",
			"val": 0.9207949543314254,
			"group": "TIC COMERCIO DE COMBUSTIVEIS LTDA ME"
		}
	],
	"links": [
		{
			"source": -100,
			"target": "LUCAS GEDEON SAMPAIO",
			"value": 16500
		},
		{
			"source": "LUCAS GEDEON SAMPAIO",
			"target": 30356,
			"value": 5500
		},
		{
			"source": "LUCAS GEDEON SAMPAIO",
			"target": 30319,
			"value": 5500
		},
		{
			"source": "LUCAS GEDEON SAMPAIO",
			"target": 30291,
			"value": 5500
		},
		{
			"source": -100,
			"target": "Cia Aérea - TAM",
			"value": 22372.249999999996
		},
		{
			"source": "Cia Aérea - TAM",
			"target": 30346,
			"value": 1115.08
		},
		{
			"source": "Cia Aérea - TAM",
			"target": 30378,
			"value": 30
		},
		{
			"source": "Cia Aérea - TAM",
			"target": 30316,
			"value": 1402.39
		},
		{
			"source": "Cia Aérea - TAM",
			"target": 30381,
			"value": 779
		},
		{
			"source": "Cia Aérea - TAM",
			"target": 30377,
			"value": 30
		},
		{
			"source": "Cia Aérea - TAM",
			"target": 30348,
			"value": 555.08
		},
		{
			"source": "Cia Aérea - TAM",
			"target": 30347,
			"value": 553.49
		},
		{
			"source": "Cia Aérea - TAM",
			"target": 30313,
			"value": 877.98
		},
		{
			"source": "Cia Aérea - TAM",
			"target": 30343,
			"value": 409.39
		},
		{
			"source": "Cia Aérea - TAM",
			"target": 30388,
			"value": 669.39
		},
		{
			"source": "Cia Aérea - TAM",
			"target": 30376,
			"value": 45
		},
		{
			"source": "Cia Aérea - TAM",
			"target": 30345,
			"value": 555.08
		},
		{
			"source": "Cia Aérea - TAM",
			"target": 30353,
			"value": 478.98
		},
		{
			"source": "Cia Aérea - TAM",
			"target": 30383,
			"value": 975.9
		},
		{
			"source": "Cia Aérea - TAM",
			"target": 30341,
			"value": 724.98
		},
		{
			"source": "Cia Aérea - TAM",
			"target": 30380,
			"value": 30
		},
		{
			"source": "Cia Aérea - TAM",
			"target": 30382,
			"value": 695
		},
		{
			"source": "Cia Aérea - TAM",
			"target": 30351,
			"value": 501.39
		},
		{
			"source": "Cia Aérea - TAM",
			"target": 30379,
			"value": 30
		},
		{
			"source": "Cia Aérea - TAM",
			"target": 30318,
			"value": 724.98
		},
		{
			"source": "Cia Aérea - TAM",
			"target": 30344,
			"value": 559.39
		},
		{
			"source": "Cia Aérea - TAM",
			"target": 30385,
			"value": 1529.39
		},
		{
			"source": "Cia Aérea - TAM",
			"target": 30352,
			"value": 501.39
		},
		{
			"source": "Cia Aérea - TAM",
			"target": 30354,
			"value": 618.98
		},
		{
			"source": "Cia Aérea - TAM",
			"target": 30342,
			"value": 724.98
		},
		{
			"source": "Cia Aérea - TAM",
			"target": 30317,
			"value": 930.39
		},
		{
			"source": "Cia Aérea - TAM",
			"target": 30375,
			"value": 30
		},
		{
			"source": "Cia Aérea - TAM",
			"target": 30314,
			"value": 948.98
		},
		{
			"source": "Cia Aérea - TAM",
			"target": 30350,
			"value": 913.49
		},
		{
			"source": "Cia Aérea - TAM",
			"target": 30384,
			"value": 741.98
		},
		{
			"source": "Cia Aérea - TAM",
			"target": 30349,
			"value": 613.98
		},
		{
			"source": "Cia Aérea - TAM",
			"target": 30355,
			"value": 849.84
		},
		{
			"source": "Cia Aérea - TAM",
			"target": 30315,
			"value": 814.98
		},
		{
			"source": "Cia Aérea - TAM",
			"target": 30386,
			"value": 740.39
		},
		{
			"source": "Cia Aérea - TAM",
			"target": 30387,
			"value": 670.98
		},
		{
			"source": -100,
			"target": "SIN- SISTEMAS INTELIGENTES LTDA - ME",
			"value": 1650
		},
		{
			"source": "SIN- SISTEMAS INTELIGENTES LTDA - ME",
			"target": 30320,
			"value": 550
		},
		{
			"source": "SIN- SISTEMAS INTELIGENTES LTDA - ME",
			"target": 30357,
			"value": 550
		},
		{
			"source": "SIN- SISTEMAS INTELIGENTES LTDA - ME",
			"target": 30292,
			"value": 550
		},
		{
			"source": -100,
			"target": "MEIO MUNDO COMUNICAÇÃO TECNOLOGIA E INOVAÇÃO LTDA-ME",
			"value": 13500
		},
		{
			"source": "MEIO MUNDO COMUNICAÇÃO TECNOLOGIA E INOVAÇÃO LTDA-ME",
			"target": 30331,
			"value": 4500
		},
		{
			"source": "MEIO MUNDO COMUNICAÇÃO TECNOLOGIA E INOVAÇÃO LTDA-ME",
			"target": 30364,
			"value": 4500
		},
		{
			"source": "MEIO MUNDO COMUNICAÇÃO TECNOLOGIA E INOVAÇÃO LTDA-ME",
			"target": 30332,
			"value": 4500
		},
		{
			"source": -100,
			"target": "CELULAR FUNCIONAL",
			"value": 759.13
		},
		{
			"source": "CELULAR FUNCIONAL",
			"target": 30367,
			"value": 9.09
		},
		{
			"source": "CELULAR FUNCIONAL",
			"target": 30300,
			"value": 77.08
		},
		{
			"source": "CELULAR FUNCIONAL",
			"target": 30333,
			"value": 14.08
		},
		{
			"source": "CELULAR FUNCIONAL",
			"target": 30301,
			"value": 22.2
		},
		{
			"source": "CELULAR FUNCIONAL",
			"target": 30334,
			"value": 319.12
		},
		{
			"source": "CELULAR FUNCIONAL",
			"target": 30366,
			"value": 316.93
		},
		{
			"source": "CELULAR FUNCIONAL",
			"target": 30365,
			"value": 0.63
		},
		{
			"source": -100,
			"target": "CASCOL COMBUSTIVEIS PARA VEICULOS LTDA",
			"value": 432.01
		},
		{
			"source": "CASCOL COMBUSTIVEIS PARA VEICULOS LTDA",
			"target": 30358,
			"value": 232.01
		},
		{
			"source": "CASCOL COMBUSTIVEIS PARA VEICULOS LTDA",
			"target": 30324,
			"value": 200
		},
		{
			"source": -100,
			"target": "JARJOUR FILIAL - 206 NORTE",
			"value": 150
		},
		{
			"source": "JARJOUR FILIAL - 206 NORTE",
			"target": 30360,
			"value": 150
		},
		{
			"source": -100,
			"target": "WMS COMERCIO DE ARTIGOS DE PAPELARIA LTDA-ME",
			"value": 548.2
		},
		{
			"source": "WMS COMERCIO DE ARTIGOS DE PAPELARIA LTDA-ME",
			"target": 30321,
			"value": 287
		},
		{
			"source": "WMS COMERCIO DE ARTIGOS DE PAPELARIA LTDA-ME",
			"target": 30293,
			"value": 261.2
		},
		{
			"source": -100,
			"target": "CORREIOS - TELEGRAMA",
			"value": 11.85
		},
		{
			"source": "CORREIOS - TELEGRAMA",
			"target": 30372,
			"value": 11.85
		},
		{
			"source": -100,
			"target": "CORREIOS - ENCOMENDA PAC",
			"value": 114.93
		},
		{
			"source": "CORREIOS - ENCOMENDA PAC",
			"target": 30337,
			"value": 51.86
		},
		{
			"source": "CORREIOS - ENCOMENDA PAC",
			"target": 30371,
			"value": 63.07
		},
		{
			"source": -100,
			"target": "POSTO DE COMBUSTIVEIS RODOVIARIA LTDA",
			"value": 200
		},
		{
			"source": "POSTO DE COMBUSTIVEIS RODOVIARIA LTDA",
			"target": 30329,
			"value": 200
		},
		{
			"source": -100,
			"target": "Cia Aérea - AVIANCA",
			"value": 2460.4700000000003
		},
		{
			"source": "Cia Aérea - AVIANCA",
			"target": 30307,
			"value": 903.49
		},
		{
			"source": "Cia Aérea - AVIANCA",
			"target": 30310,
			"value": 49
		},
		{
			"source": "Cia Aérea - AVIANCA",
			"target": 30309,
			"value": 708.49
		},
		{
			"source": "Cia Aérea - AVIANCA",
			"target": 30308,
			"value": 799.49
		},
		{
			"source": -100,
			"target": "ELO COMERCIO E SERVICOS LTDA",
			"value": 200.03
		},
		{
			"source": "ELO COMERCIO E SERVICOS LTDA",
			"target": 30327,
			"value": 200.03
		},
		{
			"source": -100,
			"target": "RAMAL",
			"value": 148.45000000000002
		},
		{
			"source": "RAMAL",
			"target": 30335,
			"value": 41.81
		},
		{
			"source": "RAMAL",
			"target": 30368,
			"value": 36.99
		},
		{
			"source": "RAMAL",
			"target": 30302,
			"value": 69.65
		},
		{
			"source": -100,
			"target": "Coelba Grupo Neoenergia",
			"value": 484.98
		},
		{
			"source": "Coelba Grupo Neoenergia",
			"target": 30290,
			"value": 484.98
		},
		{
			"source": -100,
			"target": "AUTO POSTO ALMENARA LTDA",
			"value": 221.72
		},
		{
			"source": "AUTO POSTO ALMENARA LTDA",
			"target": 30323,
			"value": 201.72
		},
		{
			"source": "AUTO POSTO ALMENARA LTDA",
			"target": 30294,
			"value": 20
		},
		{
			"source": -100,
			"target": "CORREIOS - SEDEX 12",
			"value": 95
		},
		{
			"source": "CORREIOS - SEDEX 12",
			"target": 30338,
			"value": 95
		},
		{
			"source": -100,
			"target": "TELEFÔNICA BRASIL S.A. - VIVO",
			"value": 231.01
		},
		{
			"source": "TELEFÔNICA BRASIL S.A. - VIVO",
			"target": 30369,
			"value": 231.01
		},
		{
			"source": -100,
			"target": "Cia Aérea - PASSAREDO",
			"value": 1233.65
		},
		{
			"source": "Cia Aérea - PASSAREDO",
			"target": 30312,
			"value": 543.57
		},
		{
			"source": "Cia Aérea - PASSAREDO",
			"target": 30311,
			"value": 690.08
		},
		{
			"source": -100,
			"target": "AUTO SHOPPING QL 06 COM. DE DER. DE PETROLEO LTDA",
			"value": 420
		},
		{
			"source": "AUTO SHOPPING QL 06 COM. DE DER. DE PETROLEO LTDA",
			"target": 30296,
			"value": 210
		},
		{
			"source": "AUTO SHOPPING QL 06 COM. DE DER. DE PETROLEO LTDA",
			"target": 30295,
			"value": 210
		},
		{
			"source": -100,
			"target": "CORREIOS - SEDEX CONVENCIONAL",
			"value": 58.91
		},
		{
			"source": "CORREIOS - SEDEX CONVENCIONAL",
			"target": 30303,
			"value": 58.91
		},
		{
			"source": -100,
			"target": "FERREIRA COMBUSTIVEIS LTDA",
			"value": 260.06
		},
		{
			"source": "FERREIRA COMBUSTIVEIS LTDA",
			"target": 30328,
			"value": 260.06
		},
		{
			"source": -100,
			"target": "UNIDAS LOCADORA DE VEÍCULOS",
			"value": 8246.099999999999
		},
		{
			"source": "UNIDAS LOCADORA DE VEÍCULOS",
			"target": 30306,
			"value": 2748.7
		},
		{
			"source": "UNIDAS LOCADORA DE VEÍCULOS",
			"target": 30374,
			"value": 2748.7
		},
		{
			"source": "UNIDAS LOCADORA DE VEÍCULOS",
			"target": 30340,
			"value": 2748.7
		},
		{
			"source": -100,
			"target": "MULTIPLICAR E SERVIÇOS LTDA EPP",
			"value": 17000
		},
		{
			"source": "MULTIPLICAR E SERVIÇOS LTDA EPP",
			"target": 30305,
			"value": 8500
		},
		{
			"source": "MULTIPLICAR E SERVIÇOS LTDA EPP",
			"target": 30373,
			"value": 8500
		},
		{
			"source": -100,
			"target": "MULTIPLICAR SERVICOS LTDA",
			"value": 8500
		},
		{
			"source": "MULTIPLICAR SERVICOS LTDA",
			"target": 30339,
			"value": 8500
		},
		{
			"source": -100,
			"target": "POSTO KALILANDIA LTDA",
			"value": 251.54
		},
		{
			"source": "POSTO KALILANDIA LTDA",
			"target": 30298,
			"value": 251.54
		},
		{
			"source": -100,
			"target": "CASTRO OLIVEIRA ADVOGADOS",
			"value": 18000
		},
		{
			"source": "CASTRO OLIVEIRA ADVOGADOS",
			"target": 30363,
			"value": 6000
		},
		{
			"source": "CASTRO OLIVEIRA ADVOGADOS",
			"target": 30299,
			"value": 6000
		},
		{
			"source": "CASTRO OLIVEIRA ADVOGADOS",
			"target": 30330,
			"value": 6000
		},
		{
			"source": -100,
			"target": "AUTO POSTO AEROPORTO LTDA",
			"value": 100
		},
		{
			"source": "AUTO POSTO AEROPORTO LTDA",
			"target": 30322,
			"value": 100
		},
		{
			"source": -100,
			"target": "PHAB DERIVADOS DE PETROLEO LTDA",
			"value": 240.01
		},
		{
			"source": "PHAB DERIVADOS DE PETROLEO LTDA",
			"target": 30361,
			"value": 240.01
		},
		{
			"source": -100,
			"target": "COMERCIO DE PETROLEO RSSILVA LTDA",
			"value": 417.47
		},
		{
			"source": "COMERCIO DE PETROLEO RSSILVA LTDA",
			"target": 30325,
			"value": 240
		},
		{
			"source": "COMERCIO DE PETROLEO RSSILVA LTDA",
			"target": 30326,
			"value": 177.47
		},
		{
			"source": -100,
			"target": "ITAPOAN DISTRIB. DE DER. DE PETROLEO LTDA",
			"value": 511.89
		},
		{
			"source": "ITAPOAN DISTRIB. DE DER. DE PETROLEO LTDA",
			"target": 30359,
			"value": 260.02
		},
		{
			"source": "ITAPOAN DISTRIB. DE DER. DE PETROLEO LTDA",
			"target": 30297,
			"value": 251.87
		},
		{
			"source": -100,
			"target": "ATACADAO DO PAPEL EIRELI",
			"value": 783.32
		},
		{
			"source": "ATACADAO DO PAPEL EIRELI",
			"target": 30289,
			"value": 783.32
		},
		{
			"source": -100,
			"target": "Chicago Prime Parrilla Ltda-ME",
			"value": 89.21
		},
		{
			"source": "Chicago Prime Parrilla Ltda-ME",
			"target": 30304,
			"value": 89.21
		},
		{
			"source": -100,
			"target": "CORREIOS - CARTA COMERCIAL",
			"value": 3.9
		},
		{
			"source": "CORREIOS - CARTA COMERCIAL",
			"target": 30370,
			"value": 1.95
		},
		{
			"source": "CORREIOS - CARTA COMERCIAL",
			"target": 30336,
			"value": 1.95
		},
		{
			"source": -100,
			"target": "TIC COMERCIO DE COMBUSTIVEIS LTDA ME",
			"value": 200.07
		},
		{
			"source": "TIC COMERCIO DE COMBUSTIVEIS LTDA ME",
			"target": 30362,
			"value": 200.07
		}
	]
}