{
	"nodes": [
		{
			"id": -100,
			"name": "RAIMUNDO COSTA"
		},
		{
			"id": -4,
			"name": "Voltar",
			"val": 50000
		},
		{
			"id": -3,
			"name": "Placeholder",
			"val": 0
		},
		{
			"id": -3,
			"name": "Visualizar fichas",
			"val": 50000
		},
		{
			"id": "JOSIMARIA DOS SANTOS",
			"name": "JOSIMARIA DOS SANTOS",
			"val": 543.3042864952457,
			"desc": 10200,
			"group": "JOSIMARIA DOS SANTOS"
		},
		{
			"id": 42489,
			"name": 5200,
			"val": 3.716003343634799,
			"group": "JOSIMARIA DOS SANTOS"
		},
		{
			"id": 42538,
			"name": 5000,
			"val": 3.6989700043360187,
			"group": "JOSIMARIA DOS SANTOS"
		},
		{
			"id": "POSTO SEGURO IV DERIVADOS DE PETROLEO LTDA.",
			"name": "POSTO SEGURO IV DERIVADOS DE PETROLEO LTDA.",
			"val": 4.806847085367111,
			"desc": 163.44,
			"group": "POSTO SEGURO IV DERIVADOS DE PETROLEO LTDA."
		},
		{
			"id": 42534,
			"name": 163.44,
			"val": 2.213358353624391,
			"group": "POSTO SEGURO IV DERIVADOS DE PETROLEO LTDA."
		},
		{
			"id": "Cia Aérea - TAM",
			"name": "Cia Aérea - TAM",
			"val": 1000.7689698761426,
			"desc": 17726.96,
			"group": "Cia Aérea - TAM"
		},
		{
			"id": 42508,
			"name": 994.98,
			"val": 2.9978143511206654,
			"group": "Cia Aérea - TAM"
		},
		{
			"id": 42504,
			"name": 30,
			"val": 1.4771212547196624,
			"group": "Cia Aérea - TAM"
		},
		{
			"id": 42559,
			"name": 30,
			"val": 1.4771212547196624,
			"group": "Cia Aérea - TAM"
		},
		{
			"id": 42565,
			"name": 30,
			"val": 1.4771212547196624,
			"group": "Cia Aérea - TAM"
		},
		{
			"id": 42560,
			"name": 30,
			"val": 1.4771212547196624,
			"group": "Cia Aérea - TAM"
		},
		{
			"id": 42501,
			"name": 30,
			"val": 1.4771212547196624,
			"group": "Cia Aérea - TAM"
		},
		{
			"id": 42576,
			"name": 290,
			"val": 2.462397997898956,
			"group": "Cia Aérea - TAM"
		},
		{
			"id": 42571,
			"name": 344.39,
			"val": 2.537050532421945,
			"group": "Cia Aérea - TAM"
		},
		{
			"id": 42575,
			"name": 553.49,
			"val": 2.7431097788117587,
			"group": "Cia Aérea - TAM"
		},
		{
			"id": 42514,
			"name": 589.98,
			"val": 2.7708372895457716,
			"group": "Cia Aérea - TAM"
		},
		{
			"id": 42512,
			"name": 589.98,
			"val": 2.7708372895457716,
			"group": "Cia Aérea - TAM"
		},
		{
			"id": 42502,
			"name": 35,
			"val": 1.5440680443502757,
			"group": "Cia Aérea - TAM"
		},
		{
			"id": 42515,
			"name": 978.39,
			"val": 2.9905120051821403,
			"group": "Cia Aérea - TAM"
		},
		{
			"id": 42563,
			"name": 30,
			"val": 1.4771212547196624,
			"group": "Cia Aérea - TAM"
		},
		{
			"id": 42569,
			"name": 588.39,
			"val": 2.769665283053242,
			"group": "Cia Aérea - TAM"
		},
		{
			"id": 42561,
			"name": 30,
			"val": 1.4771212547196624,
			"group": "Cia Aérea - TAM"
		},
		{
			"id": 42566,
			"name": 30,
			"val": 1.4771212547196624,
			"group": "Cia Aérea - TAM"
		},
		{
			"id": 42567,
			"name": 589.98,
			"val": 2.7708372895457716,
			"group": "Cia Aérea - TAM"
		},
		{
			"id": 42577,
			"name": 960.39,
			"val": 2.9824476293447675,
			"group": "Cia Aérea - TAM"
		},
		{
			"id": 42572,
			"name": 663.37,
			"val": 2.821755827254223,
			"group": "Cia Aérea - TAM"
		},
		{
			"id": 42568,
			"name": 345.98,
			"val": 2.53905099433993,
			"group": "Cia Aérea - TAM"
		},
		{
			"id": 42513,
			"name": 978.39,
			"val": 2.9905120051821403,
			"group": "Cia Aérea - TAM"
		},
		{
			"id": 42562,
			"name": 30,
			"val": 1.4771212547196624,
			"group": "Cia Aérea - TAM"
		},
		{
			"id": 42503,
			"name": 30,
			"val": 1.4771212547196624,
			"group": "Cia Aérea - TAM"
		},
		{
			"id": 42509,
			"name": 1766.39,
			"val": 3.2470865974003775,
			"group": "Cia Aérea - TAM"
		},
		{
			"id": 42500,
			"name": 30,
			"val": 1.4771212547196624,
			"group": "Cia Aérea - TAM"
		},
		{
			"id": 42511,
			"name": 983,
			"val": 2.9925535178321354,
			"group": "Cia Aérea - TAM"
		},
		{
			"id": 42516,
			"name": 294,
			"val": 2.4683473304121573,
			"group": "Cia Aérea - TAM"
		},
		{
			"id": 42570,
			"name": 345.98,
			"val": 2.53905099433993,
			"group": "Cia Aérea - TAM"
		},
		{
			"id": 42507,
			"name": 813.98,
			"val": 2.9106137341320193,
			"group": "Cia Aérea - TAM"
		},
		{
			"id": 42506,
			"name": 742.98,
			"val": 2.8709771233076236,
			"group": "Cia Aérea - TAM"
		},
		{
			"id": 42505,
			"name": 1079.39,
			"val": 3.0331783902300877,
			"group": "Cia Aérea - TAM"
		},
		{
			"id": 42510,
			"name": 2188.37,
			"val": 3.340120752475491,
			"group": "Cia Aérea - TAM"
		},
		{
			"id": 42573,
			"name": 340.08,
			"val": 2.531581091959066,
			"group": "Cia Aérea - TAM"
		},
		{
			"id": 42574,
			"name": 280.08,
			"val": 2.4472820977569762,
			"group": "Cia Aérea - TAM"
		},
		{
			"id": 42499,
			"name": 30,
			"val": 1.4771212547196624,
			"group": "Cia Aérea - TAM"
		},
		{
			"id": 42564,
			"name": 30,
			"val": 1.4771212547196624,
			"group": "Cia Aérea - TAM"
		},
		{
			"id": "REST. SUAN LOUN",
			"name": "REST. SUAN LOUN",
			"val": 1.2863603223297235,
			"desc": 55.5,
			"group": "REST. SUAN LOUN"
		},
		{
			"id": 42494,
			"name": 55.5,
			"val": 1.7442929831226763,
			"group": "REST. SUAN LOUN"
		},
		{
			"id": "AZULAO COMERCIO DE COMBUSTIVEIS EIRELI",
			"name": "AZULAO COMERCIO DE COMBUSTIVEIS EIRELI",
			"val": 13.429043305343225,
			"desc": 390.03999999999996,
			"group": "AZULAO COMERCIO DE COMBUSTIVEIS EIRELI"
		},
		{
			"id": 42521,
			"name": 195.04,
			"val": 2.290123688274307,
			"group": "AZULAO COMERCIO DE COMBUSTIVEIS EIRELI"
		},
		{
			"id": 42520,
			"name": 195,
			"val": 2.290034611362518,
			"group": "AZULAO COMERCIO DE COMBUSTIVEIS EIRELI"
		},
		{
			"id": "POSTO DE COMBUSTIVEL YASMIN LTDA",
			"name": "POSTO DE COMBUSTIVEL YASMIN LTDA",
			"val": 6.57125421716628,
			"desc": 212.49,
			"group": "POSTO DE COMBUSTIVEL YASMIN LTDA"
		},
		{
			"id": 42533,
			"name": 212.49,
			"val": 2.3273384965180517,
			"group": "POSTO DE COMBUSTIVEL YASMIN LTDA"
		},
		{
			"id": "Cia Aérea - GOL",
			"name": "Cia Aérea - GOL",
			"val": 407.80262045066405,
			"desc": 7876.670000000001,
			"group": "Cia Aérea - GOL"
		},
		{
			"id": 42556,
			"name": 1696.37,
			"val": 3.2295205834353595,
			"group": "Cia Aérea - GOL"
		},
		{
			"id": 42553,
			"name": 380.98,
			"val": 2.5809021774666374,
			"group": "Cia Aérea - GOL"
		},
		{
			"id": 42558,
			"name": 512.39,
			"val": 2.709600645297477,
			"group": "Cia Aérea - GOL"
		},
		{
			"id": 42552,
			"name": 489.39,
			"val": 2.6896550909062693,
			"group": "Cia Aérea - GOL"
		},
		{
			"id": 42557,
			"name": 1696.37,
			"val": 3.2295205834353595,
			"group": "Cia Aérea - GOL"
		},
		{
			"id": 42554,
			"name": 419.39,
			"val": 2.62261807086801,
			"group": "Cia Aérea - GOL"
		},
		{
			"id": 42555,
			"name": 915.39,
			"val": 2.961606163751603,
			"group": "Cia Aérea - GOL"
		},
		{
			"id": 42498,
			"name": 1766.39,
			"val": 3.2470865974003775,
			"group": "Cia Aérea - GOL"
		},
		{
			"id": "SERVICO NACIONAL DE APRENDIZAGEM COMERCIAL SENAC",
			"name": "SERVICO NACIONAL DE APRENDIZAGEM COMERCIAL SENAC",
			"val": 5.068495171416139,
			"desc": 170.85,
			"group": "SERVICO NACIONAL DE APRENDIZAGEM COMERCIAL SENAC"
		},
		{
			"id": 42495,
			"name": 25.58,
			"val": 1.407900540142635,
			"group": "SERVICO NACIONAL DE APRENDIZAGEM COMERCIAL SENAC"
		},
		{
			"id": 42545,
			"name": 28.3,
			"val": 1.4517864355242902,
			"group": "SERVICO NACIONAL DE APRENDIZAGEM COMERCIAL SENAC"
		},
		{
			"id": 42497,
			"name": 49.71,
			"val": 1.6964437631389993,
			"group": "SERVICO NACIONAL DE APRENDIZAGEM COMERCIAL SENAC"
		},
		{
			"id": 42496,
			"name": 33.92,
			"val": 1.5304558435846762,
			"group": "SERVICO NACIONAL DE APRENDIZAGEM COMERCIAL SENAC"
		},
		{
			"id": 42546,
			"name": 33.34,
			"val": 1.5229655954919865,
			"group": "SERVICO NACIONAL DE APRENDIZAGEM COMERCIAL SENAC"
		},
		{
			"id": "TAGUACENTRO COMER. DE DERIV. DE PETROLEO LTDA",
			"name": "TAGUACENTRO COMER. DE DERIV. DE PETROLEO LTDA",
			"val": 5.039094010240687,
			"desc": 170.02,
			"group": "TAGUACENTRO COMER. DE DERIV. DE PETROLEO LTDA"
		},
		{
			"id": 42535,
			"name": 170.02,
			"val": 2.2305000118414706,
			"group": "TAGUACENTRO COMER. DE DERIV. DE PETROLEO LTDA"
		},
		{
			"id": "Kalunga Comercio e Industria Grafica Ltda",
			"name": "Kalunga Comercio e Industria Grafica Ltda",
			"val": 27.912382953228985,
			"desc": 733.1500000000001,
			"group": "Kalunga Comercio e Industria Grafica Ltda"
		},
		{
			"id": 42478,
			"name": 591.08,
			"val": 2.771646264649876,
			"group": "Kalunga Comercio e Industria Grafica Ltda"
		},
		{
			"id": 42517,
			"name": 142.07,
			"val": 2.152502380461126,
			"group": "Kalunga Comercio e Industria Grafica Ltda"
		},
		{
			"id": "CORREIOS - CARTA COMERCIAL",
			"name": "CORREIOS - CARTA COMERCIAL",
			"val": 0.20588726591337397,
			"desc": 13.65,
			"group": "CORREIOS - CARTA COMERCIAL"
		},
		{
			"id": 42542,
			"name": 3.9,
			"val": 0.5910646070264992,
			"group": "CORREIOS - CARTA COMERCIAL"
		},
		{
			"id": 42543,
			"name": 9.75,
			"val": 0.9890046156985368,
			"group": "CORREIOS - CARTA COMERCIAL"
		},
		{
			"id": "FLAMINGO COM COMB LUB SERVICOS LTDA",
			"name": "FLAMINGO COM COMB LUB SERVICOS LTDA",
			"val": 4.395270375129759,
			"desc": 151.67,
			"group": "FLAMINGO COM COMB LUB SERVICOS LTDA"
		},
		{
			"id": 42483,
			"name": 151.67,
			"val": 2.1808996867662302,
			"group": "FLAMINGO COM COMB LUB SERVICOS LTDA"
		},
		{
			"id": "PETRO UNA COMERCIAL LTDA ME",
			"name": "PETRO UNA COMERCIAL LTDA ME",
			"val": 9.049683790465776,
			"desc": 278.56,
			"group": "PETRO UNA COMERCIAL LTDA ME"
		},
		{
			"id": 42485,
			"name": 278.56,
			"val": 2.444918753773256,
			"group": "PETRO UNA COMERCIAL LTDA ME"
		},
		{
			"id": "MARIETTA COM. DE ALIMENTOS LTDA",
			"name": "MARIETTA COM. DE ALIMENTOS LTDA",
			"val": 1.6467575278886115,
			"desc": 67.7,
			"group": "MARIETTA COM. DE ALIMENTOS LTDA"
		},
		{
			"id": 42491,
			"name": 67.7,
			"val": 1.8305886686851442,
			"group": "MARIETTA COM. DE ALIMENTOS LTDA"
		},
		{
			"id": "MARIA BONITA COMERCIO DE COMBUSTIVEIS E LUBRIFICANTES LTDA",
			"name": "MARIA BONITA COMERCIO DE COMBUSTIVEIS E LUBRIFICANTES LTDA",
			"val": 1.4176537429460445,
			"desc": 60,
			"group": "MARIA BONITA COMERCIO DE COMBUSTIVEIS E LUBRIFICANTES LTDA"
		},
		{
			"id": 42529,
			"name": 60,
			"val": 1.7781512503836436,
			"group": "MARIA BONITA COMERCIO DE COMBUSTIVEIS E LUBRIFICANTES LTDA"
		},
		{
			"id": "MAGGRI COMERCIO E REPRESENTACOES LTDA - ME",
			"name": "MAGGRI COMERCIO E REPRESENTACOES LTDA - ME",
			"val": 12.918100463151411,
			"desc": 377.3,
			"group": "MAGGRI COMERCIO E REPRESENTACOES LTDA - ME"
		},
		{
			"id": 42528,
			"name": 204.27,
			"val": 2.3102045888980056,
			"group": "MAGGRI COMERCIO E REPRESENTACOES LTDA - ME"
		},
		{
			"id": 42527,
			"name": 173.03,
			"val": 2.2381214077815117,
			"group": "MAGGRI COMERCIO E REPRESENTACOES LTDA - ME"
		},
		{
			"id": "PETROTRANS TRANSPORTES QUIMICOS E PETROQUIMICOS LTD",
			"name": "PETROTRANS TRANSPORTES QUIMICOS E PETROQUIMICOS LTD",
			"val": 6.11508495181978,
			"desc": 200,
			"group": "PETROTRANS TRANSPORTES QUIMICOS E PETROQUIMICOS LTD"
		},
		{
			"id": 42530,
			"name": 200,
			"val": 2.3010299956639813,
			"group": "PETROTRANS TRANSPORTES QUIMICOS E PETROQUIMICOS LTD"
		},
		{
			"id": "AUTO POSTO AEROPORTO LTDA",
			"name": "AUTO POSTO AEROPORTO LTDA",
			"val": 3.290272282514629,
			"desc": 119.25,
			"group": "AUTO POSTO AEROPORTO LTDA"
		},
		{
			"id": 42479,
			"name": 119.25,
			"val": 2.0764583877121514,
			"group": "AUTO POSTO AEROPORTO LTDA"
		},
		{
			"id": "I C PEREIRA COMERCIO DE DERIVADOS DE PETROLEO LTDA",
			"name": "I C PEREIRA COMERCIO DE DERIVADOS DE PETROLEO LTDA",
			"val": 5.322008735054593,
			"desc": 177.98,
			"group": "I C PEREIRA COMERCIO DE DERIVADOS DE PETROLEO LTDA"
		},
		{
			"id": 42526,
			"name": 177.98,
			"val": 2.2503712024344784,
			"group": "I C PEREIRA COMERCIO DE DERIVADOS DE PETROLEO LTDA"
		},
		{
			"id": "T BORGES DE QUEIROZ & CIA LTDA - ME",
			"name": "T BORGES DE QUEIROZ & CIA LTDA - ME",
			"val": 2.528625600276924,
			"desc": 96,
			"group": "T BORGES DE QUEIROZ & CIA LTDA - ME"
		},
		{
			"id": 42547,
			"name": 96,
			"val": 1.9822712330395684,
			"group": "T BORGES DE QUEIROZ & CIA LTDA - ME"
		},
		{
			"id": "Cia Aérea - AVIANCA",
			"name": "Cia Aérea - AVIANCA",
			"val": 38.431743775865165,
			"desc": 968.57,
			"group": "Cia Aérea - AVIANCA"
		},
		{
			"id": 42551,
			"name": 338.49,
			"val": 2.529545842861724,
			"group": "Cia Aérea - AVIANCA"
		},
		{
			"id": 42550,
			"name": 630.08,
			"val": 2.799395694458024,
			"group": "Cia Aérea - AVIANCA"
		},
		{
			"id": "POSTO ABASTECE COM DERIV DE PETROLEO AGUAS CLARAS LTDA",
			"name": "POSTO ABASTECE COM DERIV DE PETROLEO AGUAS CLARAS LTDA",
			"val": 6.1907472595572495,
			"desc": 202.08,
			"group": "POSTO ABASTECE COM DERIV DE PETROLEO AGUAS CLARAS LTDA"
		},
		{
			"id": 42486,
			"name": 202.08,
			"val": 2.3055233332112555,
			"group": "POSTO ABASTECE COM DERIV DE PETROLEO AGUAS CLARAS LTDA"
		},
		{
			"id": "AUTO POSTO JK LTDA",
			"name": "AUTO POSTO JK LTDA",
			"val": 6.903339674879563,
			"desc": 221.51,
			"group": "AUTO POSTO JK LTDA"
		},
		{
			"id": 42519,
			"name": 221.51,
			"val": 2.3453933370908584,
			"group": "AUTO POSTO JK LTDA"
		},
		{
			"id": "POSTO DA TORRE EIRELI - EPP",
			"name": "POSTO DA TORRE EIRELI - EPP",
			"val": 7.684560291591208,
			"desc": 242.51,
			"group": "POSTO DA TORRE EIRELI - EPP"
		},
		{
			"id": 42532,
			"name": 242.51,
			"val": 2.3847296516198337,
			"group": "POSTO DA TORRE EIRELI - EPP"
		},
		{
			"id": "POSTO DISBRAVE IMPERIAL LTDA",
			"name": "POSTO DISBRAVE IMPERIAL LTDA",
			"val": 4.865648840542765,
			"desc": 165.11,
			"group": "POSTO DISBRAVE IMPERIAL LTDA"
		},
		{
			"id": 42488,
			"name": 100,
			"val": 2,
			"group": "POSTO DISBRAVE IMPERIAL LTDA"
		},
		{
			"id": 42487,
			"name": 65.11,
			"val": 1.8136476953468967,
			"group": "POSTO DISBRAVE IMPERIAL LTDA"
		},
		{
			"id": "3L COMERCIO DE COMBUSTIVEIS E LUBRIFICANTES LTDA",
			"name": "3L COMERCIO DE COMBUSTIVEIS E LUBRIFICANTES LTDA",
			"val": 9.145776828219885,
			"desc": 281.07,
			"group": "3L COMERCIO DE COMBUSTIVEIS E LUBRIFICANTES LTDA"
		},
		{
			"id": 42518,
			"name": 281.07,
			"val": 2.4488144936695235,
			"group": "3L COMERCIO DE COMBUSTIVEIS E LUBRIFICANTES LTDA"
		},
		{
			"id": "COMERCIO DE COMBUSTIVEIS PENIEL LTDA - ME",
			"name": "COMERCIO DE COMBUSTIVEIS PENIEL LTDA - ME",
			"val": 7.218593906694096,
			"desc": 230.02,
			"group": "COMERCIO DE COMBUSTIVEIS PENIEL LTDA - ME"
		},
		{
			"id": 42524,
			"name": 230.02,
			"val": 2.3617655991132995,
			"group": "COMERCIO DE COMBUSTIVEIS PENIEL LTDA - ME"
		},
		{
			"id": "CASCOL COMBUSTIVEIS PARA VEICULOS LTDA",
			"name": "CASCOL COMBUSTIVEIS PARA VEICULOS LTDA",
			"val": 25.07022649884335,
			"desc": 667.93,
			"group": "CASCOL COMBUSTIVEIS PARA VEICULOS LTDA"
		},
		{
			"id": 42522,
			"name": 246.95,
			"val": 2.392609030497567,
			"group": "CASCOL COMBUSTIVEIS PARA VEICULOS LTDA"
		},
		{
			"id": 42482,
			"name": 179.98,
			"val": 2.2552242474798434,
			"group": "CASCOL COMBUSTIVEIS PARA VEICULOS LTDA"
		},
		{
			"id": 42480,
			"name": 141,
			"val": 2.1492191126553797,
			"group": "CASCOL COMBUSTIVEIS PARA VEICULOS LTDA"
		},
		{
			"id": 42481,
			"name": 100,
			"val": 2,
			"group": "CASCOL COMBUSTIVEIS PARA VEICULOS LTDA"
		},
		{
			"id": "INTERNACIONAL TRAVESSIAS SALVADOR S.A",
			"name": "INTERNACIONAL TRAVESSIAS SALVADOR S.A",
			"val": 3.685513652805624,
			"desc": 131,
			"group": "INTERNACIONAL TRAVESSIAS SALVADOR S.A"
		},
		{
			"id": 42549,
			"name": 63,
			"val": 1.7993405494535817,
			"group": "INTERNACIONAL TRAVESSIAS SALVADOR S.A"
		},
		{
			"id": 42548,
			"name": 68,
			"val": 1.8325089127062364,
			"group": "INTERNACIONAL TRAVESSIAS SALVADOR S.A"
		},
		{
			"id": "HIPER POSTO CAMINHO DAS ARVORES LTDA",
			"name": "HIPER POSTO CAMINHO DAS ARVORES LTDA",
			"val": 7.128014943778526,
			"desc": 227.58,
			"group": "HIPER POSTO CAMINHO DAS ARVORES LTDA"
		},
		{
			"id": 42525,
			"name": 227.58,
			"val": 2.357134093086434,
			"group": "HIPER POSTO CAMINHO DAS ARVORES LTDA"
		},
		{
			"id": "CORREIOS - CARTA REGISTRADA COM AR",
			"name": "CORREIOS - CARTA REGISTRADA COM AR",
			"val": 0.20172494360060628,
			"desc": 13.45,
			"group": "CORREIOS - CARTA REGISTRADA COM AR"
		},
		{
			"id": 42544,
			"name": 13.45,
			"val": 1.1287222843384268,
			"group": "CORREIOS - CARTA REGISTRADA COM AR"
		},
		{
			"id": "ALIANCA CONSULTORIA EMPRESARIAL EIRELI",
			"name": "ALIANCA CONSULTORIA EMPRESARIAL EIRELI",
			"val": 26.899557608873405,
			"desc": 710,
			"group": "ALIANCA CONSULTORIA EMPRESARIAL EIRELI"
		},
		{
			"id": 42536,
			"name": 710,
			"val": 2.8512583487190755,
			"group": "ALIANCA CONSULTORIA EMPRESARIAL EIRELI"
		},
		{
			"id": "AVIANCA BRASIL",
			"name": "AVIANCA BRASIL",
			"val": 25.958036819990085,
			"desc": 688.39,
			"group": "AVIANCA BRASIL"
		},
		{
			"id": 42540,
			"name": 688.39,
			"val": 2.8378345528577844,
			"group": "AVIANCA BRASIL"
		},
		{
			"id": "RAMAL",
			"name": "RAMAL",
			"val": 1.322044987472724,
			"desc": 56.73,
			"group": "RAMAL"
		},
		{
			"id": 42490,
			"name": 18.18,
			"val": 1.2595938788859486,
			"group": "RAMAL"
		},
		{
			"id": 42541,
			"name": 38.55,
			"val": 1.5860243823869757,
			"group": "RAMAL"
		},
		{
			"id": "PORTAL DA ILHA DISTRIBUIDORA DE COMBUSTIVEIS LTDA",
			"name": "PORTAL DA ILHA DISTRIBUIDORA DE COMBUSTIVEIS LTDA",
			"val": 8.813265656530179,
			"desc": 272.37,
			"group": "PORTAL DA ILHA DISTRIBUIDORA DE COMBUSTIVEIS LTDA"
		},
		{
			"id": 42531,
			"name": 272.37,
			"val": 2.435159270817999,
			"group": "PORTAL DA ILHA DISTRIBUIDORA DE COMBUSTIVEIS LTDA"
		},
		{
			"id": "MIRACI DA SILVA ALVES OLIVEIRA",
			"name": "MIRACI DA SILVA ALVES OLIVEIRA",
			"val": 6.163087024715315,
			"desc": 201.32,
			"group": "MIRACI DA SILVA ALVES OLIVEIRA"
		},
		{
			"id": 42493,
			"name": 144.32,
			"val": 2.1593265201978666,
			"group": "MIRACI DA SILVA ALVES OLIVEIRA"
		},
		{
			"id": 42492,
			"name": 57,
			"val": 1.7558748556724915,
			"group": "MIRACI DA SILVA ALVES OLIVEIRA"
		},
		{
			"id": "CEU 070 COMBUSTIVEIS LTDA",
			"name": "CEU 070 COMBUSTIVEIS LTDA",
			"val": 4.6779714818825395,
			"desc": 159.77,
			"group": "CEU 070 COMBUSTIVEIS LTDA"
		},
		{
			"id": 42523,
			"name": 159.77,
			"val": 2.203495235193291,
			"group": "CEU 070 COMBUSTIVEIS LTDA"
		},
		{
			"id": "Raimundo Reis",
			"name": "Raimundo Reis",
			"val": 102.74024694165198,
			"desc": 2300,
			"group": "Raimundo Reis"
		},
		{
			"id": 42539,
			"name": 2300,
			"val": 3.361727836017593,
			"group": "Raimundo Reis"
		},
		{
			"id": "MIGUEL ABDON PRAZERES & CIA LT",
			"name": "MIGUEL ABDON PRAZERES & CIA LT",
			"val": 6.194752082516166,
			"desc": 202.19,
			"group": "MIGUEL ABDON PRAZERES & CIA LT"
		},
		{
			"id": 42484,
			"name": 202.19,
			"val": 2.3057596722628215,
			"group": "MIGUEL ABDON PRAZERES & CIA LT"
		},
		{
			"id": "Foco profissional Ltda",
			"name": "Foco profissional Ltda",
			"val": 13.026180524663042,
			"desc": 380,
			"group": "Foco profissional Ltda"
		},
		{
			"id": 42537,
			"name": 380,
			"val": 2.57978359661681,
			"group": "Foco profissional Ltda"
		}
	],
	"links": [
		{
			"source": -100,
			"target": "JOSIMARIA DOS SANTOS",
			"value": 10200
		},
		{
			"source": "JOSIMARIA DOS SANTOS",
			"target": 42489,
			"value": 5200
		},
		{
			"source": "JOSIMARIA DOS SANTOS",
			"target": 42538,
			"value": 5000
		},
		{
			"source": -100,
			"target": "POSTO SEGURO IV DERIVADOS DE PETROLEO LTDA.",
			"value": 163.44
		},
		{
			"source": "POSTO SEGURO IV DERIVADOS DE PETROLEO LTDA.",
			"target": 42534,
			"value": 163.44
		},
		{
			"source": -100,
			"target": "Cia Aérea - TAM",
			"value": 17726.96
		},
		{
			"source": "Cia Aérea - TAM",
			"target": 42508,
			"value": 994.98
		},
		{
			"source": "Cia Aérea - TAM",
			"target": 42504,
			"value": 30
		},
		{
			"source": "Cia Aérea - TAM",
			"target": 42559,
			"value": 30
		},
		{
			"source": "Cia Aérea - TAM",
			"target": 42565,
			"value": 30
		},
		{
			"source": "Cia Aérea - TAM",
			"target": 42560,
			"value": 30
		},
		{
			"source": "Cia Aérea - TAM",
			"target": 42501,
			"value": 30
		},
		{
			"source": "Cia Aérea - TAM",
			"target": 42576,
			"value": 290
		},
		{
			"source": "Cia Aérea - TAM",
			"target": 42571,
			"value": 344.39
		},
		{
			"source": "Cia Aérea - TAM",
			"target": 42575,
			"value": 553.49
		},
		{
			"source": "Cia Aérea - TAM",
			"target": 42514,
			"value": 589.98
		},
		{
			"source": "Cia Aérea - TAM",
			"target": 42512,
			"value": 589.98
		},
		{
			"source": "Cia Aérea - TAM",
			"target": 42502,
			"value": 35
		},
		{
			"source": "Cia Aérea - TAM",
			"target": 42515,
			"value": 978.39
		},
		{
			"source": "Cia Aérea - TAM",
			"target": 42563,
			"value": 30
		},
		{
			"source": "Cia Aérea - TAM",
			"target": 42569,
			"value": 588.39
		},
		{
			"source": "Cia Aérea - TAM",
			"target": 42561,
			"value": 30
		},
		{
			"source": "Cia Aérea - TAM",
			"target": 42566,
			"value": 30
		},
		{
			"source": "Cia Aérea - TAM",
			"target": 42567,
			"value": 589.98
		},
		{
			"source": "Cia Aérea - TAM",
			"target": 42577,
			"value": 960.39
		},
		{
			"source": "Cia Aérea - TAM",
			"target": 42572,
			"value": 663.37
		},
		{
			"source": "Cia Aérea - TAM",
			"target": 42568,
			"value": 345.98
		},
		{
			"source": "Cia Aérea - TAM",
			"target": 42513,
			"value": 978.39
		},
		{
			"source": "Cia Aérea - TAM",
			"target": 42562,
			"value": 30
		},
		{
			"source": "Cia Aérea - TAM",
			"target": 42503,
			"value": 30
		},
		{
			"source": "Cia Aérea - TAM",
			"target": 42509,
			"value": 1766.39
		},
		{
			"source": "Cia Aérea - TAM",
			"target": 42500,
			"value": 30
		},
		{
			"source": "Cia Aérea - TAM",
			"target": 42511,
			"value": 983
		},
		{
			"source": "Cia Aérea - TAM",
			"target": 42516,
			"value": 294
		},
		{
			"source": "Cia Aérea - TAM",
			"target": 42570,
			"value": 345.98
		},
		{
			"source": "Cia Aérea - TAM",
			"target": 42507,
			"value": 813.98
		},
		{
			"source": "Cia Aérea - TAM",
			"target": 42506,
			"value": 742.98
		},
		{
			"source": "Cia Aérea - TAM",
			"target": 42505,
			"value": 1079.39
		},
		{
			"source": "Cia Aérea - TAM",
			"target": 42510,
			"value": 2188.37
		},
		{
			"source": "Cia Aérea - TAM",
			"target": 42573,
			"value": 340.08
		},
		{
			"source": "Cia Aérea - TAM",
			"target": 42574,
			"value": 280.08
		},
		{
			"source": "Cia Aérea - TAM",
			"target": 42499,
			"value": 30
		},
		{
			"source": "Cia Aérea - TAM",
			"target": 42564,
			"value": 30
		},
		{
			"source": -100,
			"target": "REST. SUAN LOUN",
			"value": 55.5
		},
		{
			"source": "REST. SUAN LOUN",
			"target": 42494,
			"value": 55.5
		},
		{
			"source": -100,
			"target": "AZULAO COMERCIO DE COMBUSTIVEIS EIRELI",
			"value": 390.03999999999996
		},
		{
			"source": "AZULAO COMERCIO DE COMBUSTIVEIS EIRELI",
			"target": 42521,
			"value": 195.04
		},
		{
			"source": "AZULAO COMERCIO DE COMBUSTIVEIS EIRELI",
			"target": 42520,
			"value": 195
		},
		{
			"source": -100,
			"target": "POSTO DE COMBUSTIVEL YASMIN LTDA",
			"value": 212.49
		},
		{
			"source": "POSTO DE COMBUSTIVEL YASMIN LTDA",
			"target": 42533,
			"value": 212.49
		},
		{
			"source": -100,
			"target": "Cia Aérea - GOL",
			"value": 7876.670000000001
		},
		{
			"source": "Cia Aérea - GOL",
			"target": 42556,
			"value": 1696.37
		},
		{
			"source": "Cia Aérea - GOL",
			"target": 42553,
			"value": 380.98
		},
		{
			"source": "Cia Aérea - GOL",
			"target": 42558,
			"value": 512.39
		},
		{
			"source": "Cia Aérea - GOL",
			"target": 42552,
			"value": 489.39
		},
		{
			"source": "Cia Aérea - GOL",
			"target": 42557,
			"value": 1696.37
		},
		{
			"source": "Cia Aérea - GOL",
			"target": 42554,
			"value": 419.39
		},
		{
			"source": "Cia Aérea - GOL",
			"target": 42555,
			"value": 915.39
		},
		{
			"source": "Cia Aérea - GOL",
			"target": 42498,
			"value": 1766.39
		},
		{
			"source": -100,
			"target": "SERVICO NACIONAL DE APRENDIZAGEM COMERCIAL SENAC",
			"value": 170.85
		},
		{
			"source": "SERVICO NACIONAL DE APRENDIZAGEM COMERCIAL SENAC",
			"target": 42495,
			"value": 25.58
		},
		{
			"source": "SERVICO NACIONAL DE APRENDIZAGEM COMERCIAL SENAC",
			"target": 42545,
			"value": 28.3
		},
		{
			"source": "SERVICO NACIONAL DE APRENDIZAGEM COMERCIAL SENAC",
			"target": 42497,
			"value": 49.71
		},
		{
			"source": "SERVICO NACIONAL DE APRENDIZAGEM COMERCIAL SENAC",
			"target": 42496,
			"value": 33.92
		},
		{
			"source": "SERVICO NACIONAL DE APRENDIZAGEM COMERCIAL SENAC",
			"target": 42546,
			"value": 33.34
		},
		{
			"source": -100,
			"target": "TAGUACENTRO COMER. DE DERIV. DE PETROLEO LTDA",
			"value": 170.02
		},
		{
			"source": "TAGUACENTRO COMER. DE DERIV. DE PETROLEO LTDA",
			"target": 42535,
			"value": 170.02
		},
		{
			"source": -100,
			"target": "Kalunga Comercio e Industria Grafica Ltda",
			"value": 733.1500000000001
		},
		{
			"source": "Kalunga Comercio e Industria Grafica Ltda",
			"target": 42478,
			"value": 591.08
		},
		{
			"source": "Kalunga Comercio e Industria Grafica Ltda",
			"target": 42517,
			"value": 142.07
		},
		{
			"source": -100,
			"target": "CORREIOS - CARTA COMERCIAL",
			"value": 13.65
		},
		{
			"source": "CORREIOS - CARTA COMERCIAL",
			"target": 42542,
			"value": 3.9
		},
		{
			"source": "CORREIOS - CARTA COMERCIAL",
			"target": 42543,
			"value": 9.75
		},
		{
			"source": -100,
			"target": "FLAMINGO COM COMB LUB SERVICOS LTDA",
			"value": 151.67
		},
		{
			"source": "FLAMINGO COM COMB LUB SERVICOS LTDA",
			"target": 42483,
			"value": 151.67
		},
		{
			"source": -100,
			"target": "PETRO UNA COMERCIAL LTDA ME",
			"value": 278.56
		},
		{
			"source": "PETRO UNA COMERCIAL LTDA ME",
			"target": 42485,
			"value": 278.56
		},
		{
			"source": -100,
			"target": "MARIETTA COM. DE ALIMENTOS LTDA",
			"value": 67.7
		},
		{
			"source": "MARIETTA COM. DE ALIMENTOS LTDA",
			"target": 42491,
			"value": 67.7
		},
		{
			"source": -100,
			"target": "MARIA BONITA COMERCIO DE COMBUSTIVEIS E LUBRIFICANTES LTDA",
			"value": 60
		},
		{
			"source": "MARIA BONITA COMERCIO DE COMBUSTIVEIS E LUBRIFICANTES LTDA",
			"target": 42529,
			"value": 60
		},
		{
			"source": -100,
			"target": "MAGGRI COMERCIO E REPRESENTACOES LTDA - ME",
			"value": 377.3
		},
		{
			"source": "MAGGRI COMERCIO E REPRESENTACOES LTDA - ME",
			"target": 42528,
			"value": 204.27
		},
		{
			"source": "MAGGRI COMERCIO E REPRESENTACOES LTDA - ME",
			"target": 42527,
			"value": 173.03
		},
		{
			"source": -100,
			"target": "PETROTRANS TRANSPORTES QUIMICOS E PETROQUIMICOS LTD",
			"value": 200
		},
		{
			"source": "PETROTRANS TRANSPORTES QUIMICOS E PETROQUIMICOS LTD",
			"target": 42530,
			"value": 200
		},
		{
			"source": -100,
			"target": "AUTO POSTO AEROPORTO LTDA",
			"value": 119.25
		},
		{
			"source": "AUTO POSTO AEROPORTO LTDA",
			"target": 42479,
			"value": 119.25
		},
		{
			"source": -100,
			"target": "I C PEREIRA COMERCIO DE DERIVADOS DE PETROLEO LTDA",
			"value": 177.98
		},
		{
			"source": "I C PEREIRA COMERCIO DE DERIVADOS DE PETROLEO LTDA",
			"target": 42526,
			"value": 177.98
		},
		{
			"source": -100,
			"target": "T BORGES DE QUEIROZ & CIA LTDA - ME",
			"value": 96
		},
		{
			"source": "T BORGES DE QUEIROZ & CIA LTDA - ME",
			"target": 42547,
			"value": 96
		},
		{
			"source": -100,
			"target": "Cia Aérea - AVIANCA",
			"value": 968.57
		},
		{
			"source": "Cia Aérea - AVIANCA",
			"target": 42551,
			"value": 338.49
		},
		{
			"source": "Cia Aérea - AVIANCA",
			"target": 42550,
			"value": 630.08
		},
		{
			"source": -100,
			"target": "POSTO ABASTECE COM DERIV DE PETROLEO AGUAS CLARAS LTDA",
			"value": 202.08
		},
		{
			"source": "POSTO ABASTECE COM DERIV DE PETROLEO AGUAS CLARAS LTDA",
			"target": 42486,
			"value": 202.08
		},
		{
			"source": -100,
			"target": "AUTO POSTO JK LTDA",
			"value": 221.51
		},
		{
			"source": "AUTO POSTO JK LTDA",
			"target": 42519,
			"value": 221.51
		},
		{
			"source": -100,
			"target": "POSTO DA TORRE EIRELI - EPP",
			"value": 242.51
		},
		{
			"source": "POSTO DA TORRE EIRELI - EPP",
			"target": 42532,
			"value": 242.51
		},
		{
			"source": -100,
			"target": "POSTO DISBRAVE IMPERIAL LTDA",
			"value": 165.11
		},
		{
			"source": "POSTO DISBRAVE IMPERIAL LTDA",
			"target": 42488,
			"value": 100
		},
		{
			"source": "POSTO DISBRAVE IMPERIAL LTDA",
			"target": 42487,
			"value": 65.11
		},
		{
			"source": -100,
			"target": "3L COMERCIO DE COMBUSTIVEIS E LUBRIFICANTES LTDA",
			"value": 281.07
		},
		{
			"source": "3L COMERCIO DE COMBUSTIVEIS E LUBRIFICANTES LTDA",
			"target": 42518,
			"value": 281.07
		},
		{
			"source": -100,
			"target": "COMERCIO DE COMBUSTIVEIS PENIEL LTDA - ME",
			"value": 230.02
		},
		{
			"source": "COMERCIO DE COMBUSTIVEIS PENIEL LTDA - ME",
			"target": 42524,
			"value": 230.02
		},
		{
			"source": -100,
			"target": "CASCOL COMBUSTIVEIS PARA VEICULOS LTDA",
			"value": 667.93
		},
		{
			"source": "CASCOL COMBUSTIVEIS PARA VEICULOS LTDA",
			"target": 42522,
			"value": 246.95
		},
		{
			"source": "CASCOL COMBUSTIVEIS PARA VEICULOS LTDA",
			"target": 42482,
			"value": 179.98
		},
		{
			"source": "CASCOL COMBUSTIVEIS PARA VEICULOS LTDA",
			"target": 42480,
			"value": 141
		},
		{
			"source": "CASCOL COMBUSTIVEIS PARA VEICULOS LTDA",
			"target": 42481,
			"value": 100
		},
		{
			"source": -100,
			"target": "INTERNACIONAL TRAVESSIAS SALVADOR S.A",
			"value": 131
		},
		{
			"source": "INTERNACIONAL TRAVESSIAS SALVADOR S.A",
			"target": 42549,
			"value": 63
		},
		{
			"source": "INTERNACIONAL TRAVESSIAS SALVADOR S.A",
			"target": 42548,
			"value": 68
		},
		{
			"source": -100,
			"target": "HIPER POSTO CAMINHO DAS ARVORES LTDA",
			"value": 227.58
		},
		{
			"source": "HIPER POSTO CAMINHO DAS ARVORES LTDA",
			"target": 42525,
			"value": 227.58
		},
		{
			"source": -100,
			"target": "CORREIOS - CARTA REGISTRADA COM AR",
			"value": 13.45
		},
		{
			"source": "CORREIOS - CARTA REGISTRADA COM AR",
			"target": 42544,
			"value": 13.45
		},
		{
			"source": -100,
			"target": "ALIANCA CONSULTORIA EMPRESARIAL EIRELI",
			"value": 710
		},
		{
			"source": "ALIANCA CONSULTORIA EMPRESARIAL EIRELI",
			"target": 42536,
			"value": 710
		},
		{
			"source": -100,
			"target": "AVIANCA BRASIL",
			"value": 688.39
		},
		{
			"source": "AVIANCA BRASIL",
			"target": 42540,
			"value": 688.39
		},
		{
			"source": -100,
			"target": "RAMAL",
			"value": 56.73
		},
		{
			"source": "RAMAL",
			"target": 42490,
			"value": 18.18
		},
		{
			"source": "RAMAL",
			"target": 42541,
			"value": 38.55
		},
		{
			"source": -100,
			"target": "PORTAL DA ILHA DISTRIBUIDORA DE COMBUSTIVEIS LTDA",
			"value": 272.37
		},
		{
			"source": "PORTAL DA ILHA DISTRIBUIDORA DE COMBUSTIVEIS LTDA",
			"target": 42531,
			"value": 272.37
		},
		{
			"source": -100,
			"target": "MIRACI DA SILVA ALVES OLIVEIRA",
			"value": 201.32
		},
		{
			"source": "MIRACI DA SILVA ALVES OLIVEIRA",
			"target": 42493,
			"value": 144.32
		},
		{
			"source": "MIRACI DA SILVA ALVES OLIVEIRA",
			"target": 42492,
			"value": 57
		},
		{
			"source": -100,
			"target": "CEU 070 COMBUSTIVEIS LTDA",
			"value": 159.77
		},
		{
			"source": "CEU 070 COMBUSTIVEIS LTDA",
			"target": 42523,
			"value": 159.77
		},
		{
			"source": -100,
			"target": "Raimundo Reis",
			"value": 2300
		},
		{
			"source": "Raimundo Reis",
			"target": 42539,
			"value": 2300
		},
		{
			"source": -100,
			"target": "MIGUEL ABDON PRAZERES & CIA LT",
			"value": 202.19
		},
		{
			"source": "MIGUEL ABDON PRAZERES & CIA LT",
			"target": 42484,
			"value": 202.19
		},
		{
			"source": -100,
			"target": "Foco profissional Ltda",
			"value": 380
		},
		{
			"source": "Foco profissional Ltda",
			"target": 42537,
			"value": 380
		}
	]
}